{
    "Monster_1": {
        "level": 5,
        "name": "slime",
        "max_hp": 80,
        "stats": {
            "str": 6,
            "dex": 4
        }
    },
    "Monster_2": {
        "level": 11,
        "name": "Bing chilling slime",
        "max_hp": 111,
        "stats": {
            "str": 11,
            "dex": 11
        }
    },
    "Monster_3": {
        "level": 8,
        "name": "Wolf",
        "max_hp": 80,
        "stats": {
            "str": 6,
            "dex": 4
        }
    },
    "Monster_4": {
        "level": 15,
        "name": "Great Wolf",
        "max_hp": 150,
        "stats": {
            "str": 18,
            "dex": 15
        }
    },
    "Monster_5": {
        "level": 5,
        "name": "pig",
        "max_hp": 80,
        "stats": {
            "str": 0,
            "dex": 10
        }
    },
    "Monster_6": {
        "level": 10,
        "name": "fantôme",
        "max_hp": 50,
        "stats": {
            "str": 30,
            "dex": 2
        }
    },
    "Monster_7": {
        "level": 16,
        "name": "champignon toxique",
        "max_hp": 120,
        "stats": {
            "str": 12,
            "dex": 16
        }
    },
    "Monster_8": {
        "level": 20,
        "name": "guerrier squelette",
        "max_hp": 140,
        "stats": {
            "str": 20,
            "dex": 20
        }
    },
    "Monster_9": {
        "level": 23,
        "name": "mage squelette",
        "max_hp": 100,
        "stats": {
            "str": 30,
            "dex": 15
        }
    },
    "Monster_10": {
        "level": 50,
        "name": "Hugo le 1000 et une mensonge",
        "max_hp": 200,
        "stats": {
            "str": 30,
            "dex": 40
        }
    }
}